{
	"state": 1,
	"msg": "success",
	"body": {
		"total": 100,
		"pages": 10,
		"list": [{
			"id": 1,
			"userId": 1,
			"rank": 1,
			"likeNum": 1000,
			"manName": "uu1",
			"womanName": "uupt",
			"sweetCovers": "https://image.dianliangfanxing.cn/production/works/9547810896114340bfc0bd22fda5c2f9.jpg/500"
		}, {
			"id": 2,
			"userId": 2,
			"rank": 2,
			"likeNum": 900,
			"manName": "uu2",
			"womanName": "uupttt",
			"sweetCovers": "https://image.dianliangfanxing.cn/production/works/2bb45452c80d4d8782d7503c300d87cb.jpg/500"
		},
		{
			"id": 3,
			"userId": 2,
			"rank": 2,
			"likeNum": 900,
			"manName": "uu3",
			"womanName": "uupttt",
			"sweetCovers": "https://image.dianliangfanxing.cn/production/works/a89ef282b1284f41879d608315e51448.jpg/500"
		},
		{
			"id": 4,
			"userId": 2,
			"rank": 2,
			"likeNum": 900,
			"manName": "uu4",
			"womanName": "uupttt",
			"sweetCovers": "https://image.dianliangfanxing.cn/production/works/0c97b30de79e49dabde252dfc7b9e905.png/500"
		},
		{
			"id": 5,
			"userId": 2,
			"rank": 2,
			"likeNum": 900,
			"manName": "uu5",
			"womanName": "uupttt",
			"sweetCovers": "https://image.dianliangfanxing.cn/production/works/f3ce80f0f8e749a5a27c1c2dbecf5a4c.jpg/500"
		}]
	}
}